<?xml version="1.0"?>
<MenuItems>
  <MenuItem id="checkForUpdates">
    <Name>Check for Updates</Name>
    <CallbackMethod>checkForUpdates</CallbackMethod>
  </MenuItem>
  <MenuItem id="checkRateLimit">
    <Name>Check Rate Limiter</Name>
    <CallbackMethod>checkRateLimit</CallbackMethod>
  </MenuItem>
  <MenuItem id="toggleDebugging">
    <Name>Toggle Debugging</Name>
    <CallbackMethod>toggleDebugging</CallbackMethod>
  </MenuItem>

	<MenuItem id="separator1" type="separator" />

  <MenuItem id="testUpdateCheck">
    <Name>Test Update Check</Name>
    <CallbackMethod>testUpdateCheck</CallbackMethod>
  </MenuItem>
</MenuItems>
